odoo10_addon_shopinvader_promotion_rule-10.0.1.3.0-nspkg.pth
odoo/addons/shopinvader_promotion_rule/README.rst
odoo/addons/shopinvader_promotion_rule/__init__.py
odoo/addons/shopinvader_promotion_rule/__manifest__.py
odoo/addons/shopinvader_promotion_rule/models/__init__.py
odoo/addons/shopinvader_promotion_rule/models/sale_order.py
odoo/addons/shopinvader_promotion_rule/models/sale_promotion_rule.py
odoo/addons/shopinvader_promotion_rule/services/__init__.py
odoo/addons/shopinvader_promotion_rule/services/cart.py
odoo/addons/shopinvader_promotion_rule/tests/__init__.py
odoo/addons/shopinvader_promotion_rule/tests/test_cart.py
odoo/addons/shopinvader_promotion_rule/views/sale_promotion_rule.xml
odoo10_addon_shopinvader_promotion_rule-10.0.1.3.0.dist-info/METADATA
odoo10_addon_shopinvader_promotion_rule-10.0.1.3.0.dist-info/WHEEL
odoo10_addon_shopinvader_promotion_rule-10.0.1.3.0.dist-info/namespace_packages.txt
odoo10_addon_shopinvader_promotion_rule-10.0.1.3.0.dist-info/top_level.txt
odoo10_addon_shopinvader_promotion_rule-10.0.1.3.0.dist-info/RECORD
