Metadata-Version: 2.1
Name: odoo10-addon-shopinvader-promotion-rule
Version: 10.0.1.3.0
Summary: Module to manage Promotion Rule with shopinvader
Home-page: https://akretion.com
Author: Akretion, ACSONE SA / NV
License: AGPL-3
Platform: UNKNOWN
Classifier: Programming Language :: Python
Classifier: Framework :: Odoo
Classifier: License :: OSI Approved :: GNU Affero General Public License v3
Requires-Python: ~=2.7
Requires-Dist: odoo10-addon-component
Requires-Dist: odoo10-addon-sale-promotion-rule
Requires-Dist: odoo10-addon-shopinvader
Requires-Dist: odoo (<10.1dev,>=10.0)
